submissionsync/__init__.py
submissionsync/__main__.py
submissionsync/cli.py
submissionsync/core.py
submissionsync/shortcuts.py
submissionsync-0.1.0.dist-info/licenses/LICENSE
submissionsync-0.1.0.dist-info/METADATA
submissionsync-0.1.0.dist-info/WHEEL
submissionsync-0.1.0.dist-info/entry_points.txt
submissionsync-0.1.0.dist-info/top_level.txt
submissionsync-0.1.0.dist-info/RECORD
