Metadata-Version: 2.4
Name: submissionsync
Version: 0.1.0
Summary: Create shortcuts to latest submitted MS teams assignment versions
Home-page: https://github.com/UTCSheffield/ms-teams-latest-submitted-version
Author: Your Name
Author-email: Martyn Eggleton <meggleton@utcsheffield.org.uk>
License: MIT
Project-URL: Homepage, https://github.com/UTCSheffield/ms-teams-latest-submitted-version
Keywords: submissions,shortcuts,assignments,windows
Requires-Python: >=3.8
License-File: LICENSE
Requires-Dist: seedir>=0.4.0
Requires-Dist: pywin32>=302
Provides-Extra: dev
Requires-Dist: pytest>=6.0; extra == "dev"
Dynamic: author
Dynamic: home-page
Dynamic: license-file
Dynamic: requires-python
